kuryr_kubernetes/__init__.py
kuryr_kubernetes/clients.py
kuryr_kubernetes/config.py
kuryr_kubernetes/constants.py
kuryr_kubernetes/exceptions.py
kuryr_kubernetes/health.py
kuryr_kubernetes/k8s_client.py
kuryr_kubernetes/linux_net_utils.py
kuryr_kubernetes/opts.py
kuryr_kubernetes/os_vif_plug_noop.py
kuryr_kubernetes/os_vif_util.py
kuryr_kubernetes/utils.py
kuryr_kubernetes/version.py
kuryr_kubernetes/watcher.py
kuryr_kubernetes/cmd/__init__.py
kuryr_kubernetes/cmd/cni.py
kuryr_kubernetes/cmd/daemon.py
kuryr_kubernetes/cmd/sanity_checks.py
kuryr_kubernetes/cmd/status.py
kuryr_kubernetes/cmd/eventlet/__init__.py
kuryr_kubernetes/cmd/eventlet/controller.py
kuryr_kubernetes/cmd/sanity/__init__.py
kuryr_kubernetes/cmd/sanity/checks.py
kuryr_kubernetes/cni/__init__.py
kuryr_kubernetes/cni/api.py
kuryr_kubernetes/cni/handlers.py
kuryr_kubernetes/cni/health.py
kuryr_kubernetes/cni/main.py
kuryr_kubernetes/cni/prometheus_exporter.py
kuryr_kubernetes/cni/utils.py
kuryr_kubernetes/cni/binding/__init__.py
kuryr_kubernetes/cni/binding/base.py
kuryr_kubernetes/cni/binding/bridge.py
kuryr_kubernetes/cni/binding/dpdk.py
kuryr_kubernetes/cni/binding/nested.py
kuryr_kubernetes/cni/binding/vhostuser.py
kuryr_kubernetes/cni/daemon/__init__.py
kuryr_kubernetes/cni/daemon/service.py
kuryr_kubernetes/cni/daemon/watcher_service.py
kuryr_kubernetes/cni/plugins/__init__.py
kuryr_kubernetes/cni/plugins/base.py
kuryr_kubernetes/cni/plugins/k8s_cni_registry.py
kuryr_kubernetes/controller/__init__.py
kuryr_kubernetes/controller/service.py
kuryr_kubernetes/controller/drivers/__init__.py
kuryr_kubernetes/controller/drivers/annotation_project.py
kuryr_kubernetes/controller/drivers/base.py
kuryr_kubernetes/controller/drivers/default_project.py
kuryr_kubernetes/controller/drivers/default_security_groups.py
kuryr_kubernetes/controller/drivers/default_subnet.py
kuryr_kubernetes/controller/drivers/lb_public_ip.py
kuryr_kubernetes/controller/drivers/lbaasv2.py
kuryr_kubernetes-10.0.0.dist-info/AUTHORS
kuryr_kubernetes-10.0.0.dist-info/LICENSE
kuryr_kubernetes-10.0.0.dist-info/METADATA
kuryr_kubernetes-10.0.0.dist-info/WHEEL
kuryr_kubernetes-10.0.0.dist-info/entry_points.txt
kuryr_kubernetes-10.0.0.dist-info/pbr.json
kuryr_kubernetes-10.0.0.dist-info/top_level.txt
kuryr_kubernetes-10.0.0.dist-info/RECORD
